nmk_rust/__init__.py
nmk_rust/cargo.yml
nmk_rust/files.yml
nmk_rust/format.yml
nmk_rust/plugin.yml
nmk_rust/resolvers.py
nmk_rust/templates/__init__.py
nmk_rust/templates/config.toml.jinja
nmk_rust/templates/manifest.toml.jinja
nmk_rust/templates/rustfmt.toml.jinja
nmk_rust-0.3.0.dist-info/LICENSE
nmk_rust-0.3.0.dist-info/METADATA
nmk_rust-0.3.0.dist-info/WHEEL
nmk_rust-0.3.0.dist-info/top_level.txt
nmk_rust-0.3.0.dist-info/RECORD
