Metadata-Version: 2.1
Name: nmk-rust
Version: 0.3.0
Summary: Rust plugin for nmk build system
Author: The dynod project
Maintainer: The dynod project
License: Mozilla Public License Version 2.0
Project-URL: Homepage, https://github.com/dynod/nmk-rust
Project-URL: Repository, https://github.com/dynod/nmk-rust
Project-URL: Issues, https://github.com/dynod/nmk/issues?q=is%3Aopen+is%3Aissue+label%3Aplugin%3Arust
Classifier: Programming Language :: Python :: 3.9
Classifier: Programming Language :: Python :: 3.10
Classifier: Programming Language :: Python :: 3.11
Classifier: Programming Language :: Python :: 3.12
Requires-Python: >=3.9
License-File: LICENSE
Requires-Dist: nmk-base>=0.26.0
